blockchainetl/__init__.py
blockchainetl/atomic_counter.py
blockchainetl/csv_utils.py
blockchainetl/exporters.py
blockchainetl/file_utils.py
blockchainetl/logging_utils.py
blockchainetl/jobs/__init__.py
blockchainetl/jobs/base_job.py
blockchainetl/jobs/exporters/__init__.py
blockchainetl/jobs/exporters/composite_item_exporter.py
blockchainetl/jobs/exporters/console_item_exporter.py
blockchainetl/jobs/exporters/gcs_item_exporter.py
blockchainetl/jobs/exporters/google_pubsub_item_exporter.py
blockchainetl/jobs/exporters/in_memory_item_exporter.py
blockchainetl/jobs/exporters/kafka_exporter.py
blockchainetl/jobs/exporters/kinesis_item_exporter.py
blockchainetl/jobs/exporters/multi_item_exporter.py
blockchainetl/jobs/exporters/postgres_item_exporter.py
blockchainetl/jobs/exporters/converters/__init__.py
blockchainetl/jobs/exporters/converters/composite_item_converter.py
blockchainetl/jobs/exporters/converters/int_to_decimal_item_converter.py
blockchainetl/jobs/exporters/converters/int_to_string_item_converter.py
blockchainetl/jobs/exporters/converters/list_field_item_converter.py
blockchainetl/jobs/exporters/converters/simple_item_converter.py
blockchainetl/jobs/exporters/converters/unix_timestamp_item_converter.py
blockchainetl/streaming/__init__.py
blockchainetl/streaming/postgres_utils.py
blockchainetl/streaming/streamer.py
blockchainetl/streaming/streamer_adapter_stub.py
blockchainetl/streaming/streaming_utils.py
glideetl/__init__.py
glideetl/__main__.py
glideetl/atomic_counter.py
glideetl/csv_utils.py
glideetl/erc20_abi.py
glideetl/exporters.py
glideetl/json_rpc_requests.py
glideetl/mainnet_daofork_state_changes.py
glideetl/mainnet_genesis_alloc.py
glideetl/misc_utils.py
glideetl/progress_logger.py
glideetl/thread_local_proxy.py
glideetl/utils.py
glideetl/web3_utils.py
glideetl/cli/__init__.py
glideetl/cli/export_all.py
glideetl/cli/export_blocks_and_transactions.py
glideetl/cli/export_contracts.py
glideetl/cli/export_geth_traces.py
glideetl/cli/export_origin.py
glide_etl-2.4.2.dist-info/LICENSE
glide_etl-2.4.2.dist-info/METADATA
glide_etl-2.4.2.dist-info/WHEEL
glide_etl-2.4.2.dist-info/entry_points.txt
glide_etl-2.4.2.dist-info/top_level.txt
glide_etl-2.4.2.dist-info/RECORD
